deepdiagnostics/__init__.py
deepdiagnostics/client/__init__.py
deepdiagnostics/client/client.py
deepdiagnostics/data/__init__.py
deepdiagnostics/data/data.py
deepdiagnostics/data/h5_data.py
deepdiagnostics/data/pickle_data.py
deepdiagnostics/data/simulator.py
deepdiagnostics/metrics/__init__.py
deepdiagnostics/metrics/all_sbc.py
deepdiagnostics/metrics/coverage_fraction.py
deepdiagnostics/metrics/local_two_sample.py
deepdiagnostics/metrics/metric.py
deepdiagnostics/models/__init__.py
deepdiagnostics/models/model.py
deepdiagnostics/models/sbi_model.py
deepdiagnostics/plots/__init__.py
deepdiagnostics/plots/cdf_ranks.py
deepdiagnostics/plots/coverage_fraction.py
deepdiagnostics/plots/local_two_sample.py
deepdiagnostics/plots/parity.py
deepdiagnostics/plots/plot.py
deepdiagnostics/plots/predictive_posterior_check.py
deepdiagnostics/plots/predictive_prior_check.py
deepdiagnostics/plots/ranks.py
deepdiagnostics/plots/tarp.py
deepdiagnostics/utils/__init__.py
deepdiagnostics/utils/config.py
deepdiagnostics/utils/defaults.py
deepdiagnostics/utils/plotting_utils.py
deepdiagnostics/utils/simulator_utils.py
deepdiagnostics/utils/variable_store.py
deepdiagnostics-1.0.0.dist-info/entry_points.txt
deepdiagnostics-1.0.0.dist-info/LICENSE.txt
deepdiagnostics-1.0.0.dist-info/WHEEL
deepdiagnostics-1.0.0.dist-info/METADATA
deepdiagnostics-1.0.0.dist-info/RECORD
