Metadata-Version: 2.1
Name: deepdiagnostics
Version: 1.0.0
Summary: a package for diagnosing posterior quality from inference methods
License: MIT
Author: Becky Nevin
Author-email: rnevin@fnal.gov
Requires-Python: >=3.10,<4.0
Classifier: License :: OSI Approved :: MIT License
Classifier: Programming Language :: Python :: 3
Classifier: Programming Language :: Python :: 3.10
Classifier: Programming Language :: Python :: 3.11
Requires-Dist: deprecation (>=2.1.0,<3.0.0)
Requires-Dist: getdist (>=1.4.7,<2.0.0)
Requires-Dist: h5py (>=3.10.0,<4.0.0)
Requires-Dist: matplotlib (>=3.8.3,<4.0.0)
Requires-Dist: numpy (>=1.18.5,<1.26.0)
Requires-Dist: pyarrow (>=15.0.0,<16.0.0)
Requires-Dist: sbi (>=0.22.0,<0.23.0)
Requires-Dist: scipy (>=1.6.0,<1.12.0)
Requires-Dist: tarp (>=0.1.1,<0.2.0)
